llm_intelligence/__init__.py
llm_intelligence/auto_populate.py
llm_intelligence/blueprints.py
llm_intelligence/carton_sync.py
llm_intelligence/context_gauge.py
llm_intelligence/core.py
llm_intelligence/mcp_server.py
llm_intelligence/projects.py
giint_llm_intelligence-0.1.8.dist-info/METADATA
giint_llm_intelligence-0.1.8.dist-info/WHEEL
giint_llm_intelligence-0.1.8.dist-info/entry_points.txt
giint_llm_intelligence-0.1.8.dist-info/top_level.txt
giint_llm_intelligence-0.1.8.dist-info/RECORD
