Metadata-Version: 2.4
Name: giint-llm-intelligence
Version: 0.1.8
Summary: GIINT - General Intuitive Intelligence for Neural Transformers: Multi-fire cognitive architecture
Author: Isaac
Requires-Python: >=3.8
Requires-Dist: fastmcp>=2.12.2
Dynamic: author
Dynamic: requires-python
